{
  "name": "Froala",
  "description": "Premium commercial WYSIWYG editor with modern UI and extensive plugin ecosystem",
  "icon": "🎨",
  "url": "https://froala.com/wysiwyg-editor/",
  "values": {
    "description": {
      "value": "A premium, lightweight WYSIWYG HTML editor with 30+ plugins, beautiful UI, and extensive framework support",
      "source": ["https://froala.com/wysiwyg-editor/"]
    },
    "website": {
      "value": "https://froala.com/wysiwyg-editor/",
      "source": ["https://froala.com/wysiwyg-editor/"]
    },
    "repository": {
      "value": "https://github.com/froala/wysiwyg-editor",
      "source": ["https://github.com/froala/wysiwyg-editor"]
    },
    "license": {
      "value": "Commercial",
      "source": ["https://github.com/froala/wysiwyg-editor"],
      "comment": "Commercial license required; trial available"
    },
    "initial-release": {
      "value": "2014",
      "source": ["https://github.com/froala/wysiwyg-editor"],
      "comment": "Repository created February 3, 2014"
    },
    "latest-release": {
      "value": "2025-11-19",
      "source": ["https://github.com/froala/wysiwyg-editor"],
      "comment": "v4.7.1"
    },
    "github-stars": {
      "value": 5400,
      "source": ["https://github.com/froala/wysiwyg-editor"]
    },
    "framework": {
      "value": ["vanilla", "react", "vue", "angular"],
      "source": ["https://froala.com/wysiwyg-editor/"],
      "comment": "Official packages for React, Vue, Angular, and more"
    },
    "base-library": {
      "value": null,
      "source": ["https://froala.com/wysiwyg-editor/"],
      "comment": "Original implementation; no base library"
    },
    "data-model": {
      "value": ["html", "markdown"],
      "source": ["https://froala.com/blog/editor/tutorials/how-to-use-the-froala-markdown-plugin-item-by-item/"],
      "comment": "HTML primary; Markdown plugin available"
    },
    "typescript": {
      "value": true,
      "source": ["https://github.com/froala/wysiwyg-editor"],
      "comment": "TypeScript definitions included (index.d.ts)"
    },
    "bundle-size": {
      "value": 150000,
      "source": ["https://github.com/froala/react-froala-wysiwyg/issues/42"],
      "comment": "~490KB for full packaged version; modular plugins reduce size"
    },
    "headless": {
      "value": false,
      "source": ["https://froala.com/wysiwyg-editor/"],
      "comment": "UI-focused; not designed for headless use"
    },
    "realtime-collab": {
      "value": false,
      "source": ["https://froala.com/wysiwyg-editor/features/"],
      "comment": "Not a built-in feature"
    },
    "collab-protocol": {
      "value": [],
      "source": ["https://froala.com/wysiwyg-editor/"]
    },
    "offline-support": {
      "value": false,
      "source": ["https://froala.com/wysiwyg-editor/"]
    },
    "change-tracking": {
      "value": true,
      "source": ["https://froala.com/wysiwyg-editor/features/"],
      "comment": "Track changes feature available"
    },
    "comments": {
      "value": false,
      "source": ["https://froala.com/wysiwyg-editor/features/"],
      "comment": "Not mentioned as a feature"
    },
    "tables": {
      "value": true,
      "source": ["https://froala.com/wysiwyg-editor/features/"],
      "comment": "Advanced table operations with cell selection and resize"
    },
    "images": {
      "value": true,
      "source": ["https://froala.com/wysiwyg-editor/features/"],
      "comment": "Full image editor with crop, flip, rotate, filters"
    },
    "embeds": {
      "value": true,
      "source": ["https://froala.com/wysiwyg-editor/features/"],
      "comment": "500+ embed providers via embed.ly; video embedding"
    },
    "code-blocks": {
      "value": true,
      "source": ["https://froala.com/blog/editor/tutorials/how-to-use-the-froala-markdown-plugin-item-by-item/"],
      "comment": "Fenced code blocks with syntax highlighting"
    },
    "math-latex": {
      "value": false,
      "source": ["https://froala.com/wysiwyg-editor/features/"],
      "comment": "Not mentioned in features"
    },
    "mentions": {
      "value": true,
      "source": ["https://froala.com/blog/general/six-features-you-can-deliver-instantly-html-editor-software/"],
      "comment": "@ mentions with autocomplete"
    },
    "emoji-picker": {
      "value": true,
      "source": ["https://froala.com/wysiwyg-editor/features/"],
      "comment": "Emoticons plugin available"
    },
    "slash-commands": {
      "value": false,
      "source": ["https://froala.com/wysiwyg-editor/features/"],
      "comment": "Not a built-in feature"
    },
    "drag-drop-blocks": {
      "value": true,
      "source": ["https://froala.com/wysiwyg-editor/features/"],
      "comment": "Drag & drop file upload; block manipulation"
    },
    "nested-blocks": {
      "value": true,
      "source": ["https://froala.com/wysiwyg-editor/features/"],
      "comment": "Lists and nested content supported"
    },
    "toolbar": {
      "value": ["fixed", "floating", "customizable"],
      "source": ["https://froala.com/wysiwyg-editor/features/"],
      "comment": "Customizable toolbar with plugins"
    },
    "mobile-support": {
      "value": true,
      "source": ["https://froala.com/wysiwyg-editor/features/"],
      "comment": "Mobile-responsive design"
    },
    "keyboard-shortcuts": {
      "value": true,
      "source": ["https://froala.com/wysiwyg-editor/features/"]
    },
    "accessibility": {
      "value": true,
      "source": ["https://froala.com/wysiwyg-editor/features/"],
      "comment": "WCAG compliance mentioned"
    },
    "undo-redo": {
      "value": true,
      "source": ["https://froala.com/wysiwyg-editor/features/"]
    },
    "find-replace": {
      "value": false,
      "source": ["https://froala.com/wysiwyg-editor/features/"],
      "comment": "Not mentioned as a feature"
    },
    "spell-check": {
      "value": true,
      "source": ["https://froala.com/wysiwyg-editor/features/"],
      "comment": "Browser native spell check"
    },
    "plugin-system": {
      "value": true,
      "source": ["https://froala.com/wysiwyg-editor/features/"],
      "comment": "30+ official plugins; extensible architecture"
    },
    "custom-nodes": {
      "value": true,
      "source": ["https://froala.com/wysiwyg-editor/features/"],
      "comment": "Custom plugins can add elements"
    },
    "custom-marks": {
      "value": true,
      "source": ["https://froala.com/wysiwyg-editor/features/"]
    },
    "schema-customization": {
      "value": true,
      "source": ["https://froala.com/wysiwyg-editor/features/"],
      "comment": "Customizable via plugins"
    },
    "themes": {
      "value": true,
      "source": ["https://froala.com/wysiwyg-editor/features/"],
      "comment": "Multiple themes available"
    },
    "documentation-quality": {
      "value": 4,
      "source": ["https://froala.com/wysiwyg-editor/docs/"],
      "comment": "Good documentation with examples and API reference"
    },
    "npm-downloads": {
      "value": 236207,
      "source": ["https://www.npmjs.com/package/froala-editor"]
    },
    "active-maintenance": {
      "value": true,
      "source": ["https://github.com/froala/wysiwyg-editor"],
      "comment": "140 releases; v4.7.1 released November 2025"
    },
    "commercial-support": {
      "value": true,
      "source": ["https://froala.com/wysiwyg-editor/"],
      "comment": "Commercial product with paid licensing and support"
    }
  }
}
