{
  "candidates": [
    { "id": "prosemirror", "shownByDefault": true },
    { "id": "tiptap", "shownByDefault": true },
    { "id": "slate", "shownByDefault": true },
    { "id": "lexical", "shownByDefault": true },
    { "id": "quill", "shownByDefault": false },
    { "id": "ckeditor5", "shownByDefault": false },
    { "id": "tinymce", "shownByDefault": false },
    { "id": "draft-js", "shownByDefault": false },
    { "id": "yoopta-editor", "shownByDefault": false },
    { "id": "novel", "shownByDefault": false },
    { "id": "redactor", "shownByDefault": false },
    { "id": "editor-js", "shownByDefault": false },
    { "id": "milkdown", "shownByDefault": false },
    { "id": "toast-ui-editor", "shownByDefault": false },
    { "id": "remirror", "shownByDefault": false },
    { "id": "blocknote", "shownByDefault": false },
    { "id": "plate", "shownByDefault": false },
    { "id": "froala", "shownByDefault": false },
    { "id": "summernote", "shownByDefault": false },
    { "id": "jodit", "shownByDefault": false },
    { "id": "etherpad", "shownByDefault": false }
  ]
}
