{
  "name": "PickleDB",
  "description": "Lightweight and simple key-value store with JSON/YAML/CBOR/Bincode serialization",
  "icon": null,
  "url": "https://github.com/seladb/pickledb-rs",
  "values": {
    "description": {
      "value": "Lightweight and simple key-value store with JSON/YAML/CBOR/Bincode serialization",
      "source": ["https://github.com/seladb/pickledb-rs"],
      "comment": "Rust port of Python's PickleDB; designed for simplicity over performance"
    },
    "license": {
      "value": ["mit"],
      "source": ["https://github.com/seladb/pickledb-rs"]
    },
    "implementation": {
      "value": ["pure-rust"],
      "source": ["https://github.com/seladb/pickledb-rs"]
    },
    "repository": {
      "value": "https://github.com/seladb/pickledb-rs"
    },
    "crates-io": {
      "value": "https://crates.io/crates/pickledb"
    },
    "documentation": {
      "value": "https://docs.rs/pickledb"
    },
    "first-release": {
      "value": "2019",
      "source": ["https://lib.rs/crates/pickledb"],
      "comment": "First release January 16, 2019"
    },
    "latest-version": {
      "value": "0.5.1",
      "source": ["https://lib.rs/crates/pickledb"],
      "comment": "As of December 2025"
    },
    "database-type": {
      "value": ["key-value"],
      "source": ["https://github.com/seladb/pickledb-rs"]
    },
    "schema-model": {
      "value": ["schemaless"],
      "source": ["https://github.com/seladb/pickledb-rs"],
      "comment": "Stores any serde-serializable value"
    },
    "query-language": {
      "value": "API-only",
      "source": ["https://docs.rs/pickledb"],
      "comment": "Simple get/set API"
    },
    "transactions": {
      "value": false,
      "source": ["https://docs.rs/pickledb"],
      "comment": "No transaction support"
    },
    "range-queries": {
      "value": false,
      "source": ["https://docs.rs/pickledb"],
      "comment": "Key lookup only"
    },
    "secondary-indexes": {
      "value": false,
      "source": ["https://docs.rs/pickledb"],
      "comment": "No secondary indexes"
    },
    "in-memory-mode": {
      "value": true,
      "source": ["https://github.com/seladb/pickledb-rs"],
      "comment": "Entire database is kept in memory; dumped to file on save"
    },
    "persistent-storage": {
      "value": true,
      "source": ["https://github.com/seladb/pickledb-rs"],
      "comment": "Persists to file; configurable dump policies"
    },
    "storage-architecture": {
      "value": "In-memory HashMap with file dump",
      "source": ["https://github.com/seladb/pickledb-rs"],
      "comment": "Entire store held in memory, periodically dumped to file"
    },
    "compression": {
      "value": false,
      "source": ["https://docs.rs/pickledb"]
    },
    "encryption-at-rest": {
      "value": false,
      "source": ["https://docs.rs/pickledb"]
    },
    "memory-mapped-io": {
      "value": false,
      "source": ["https://docs.rs/pickledb"]
    },
    "max-db-size": {
      "value": "Limited by available RAM",
      "source": ["https://github.com/seladb/pickledb-rs"],
      "comment": "Entire database must fit in memory"
    },
    "pure-rust": {
      "value": true,
      "source": ["https://github.com/seladb/pickledb-rs"],
      "comment": "100% pure Rust"
    },
    "async-support": {
      "value": ["sync-only"],
      "source": ["https://docs.rs/pickledb"],
      "comment": "Synchronous API only"
    },
    "api-safety": {
      "value": ["fully-safe"],
      "source": ["https://github.com/seladb/pickledb-rs"],
      "comment": "Safe Rust API"
    },
    "idiomatic-api": {
      "value": 4,
      "source": ["https://docs.rs/pickledb"],
      "comment": "Simple and intuitive API; uses Options and Results"
    },
    "type-safety": {
      "value": ["generic"],
      "source": ["https://docs.rs/pickledb"],
      "comment": "Generic API works with any serde-serializable type"
    },
    "serde-integration": {
      "value": true,
      "source": ["https://github.com/seladb/pickledb-rs"],
      "comment": "Native serde support with multiple serialization formats"
    },
    "no-std": {
      "value": false,
      "source": ["https://docs.rs/pickledb"],
      "comment": "Requires std"
    },
    "wasm-compatible": {
      "value": false,
      "source": ["https://docs.rs/pickledb"],
      "comment": "Not WASM compatible"
    },
    "acid-compliant": {
      "value": false,
      "source": ["https://docs.rs/pickledb"],
      "comment": "No ACID guarantees"
    },
    "crash-recovery": {
      "value": false,
      "source": ["https://github.com/seladb/pickledb-rs"],
      "comment": "Data between dumps may be lost on crash"
    },
    "concurrent-readers": {
      "value": false,
      "source": ["https://github.com/seladb/pickledb-rs"],
      "comment": "Single-threaded; runs in user's process and thread"
    },
    "concurrent-writers": {
      "value": false,
      "source": ["https://github.com/seladb/pickledb-rs"],
      "comment": "Single-threaded"
    },
    "multi-process": {
      "value": false,
      "source": ["https://github.com/seladb/pickledb-rs"],
      "comment": "Single process only"
    },
    "write-ahead-log": {
      "value": false,
      "source": ["https://docs.rs/pickledb"]
    },
    "maturity": {
      "value": ["stable"],
      "source": ["https://lib.rs/crates/pickledb"],
      "comment": "Simple and stable; no longer actively developed but functional"
    },
    "linux": {
      "value": true,
      "source": ["https://github.com/seladb/pickledb-rs"]
    },
    "macos": {
      "value": true,
      "source": ["https://github.com/seladb/pickledb-rs"]
    },
    "windows": {
      "value": true,
      "source": ["https://github.com/seladb/pickledb-rs"]
    },
    "ios": {
      "value": null,
      "comment": "Not explicitly documented"
    },
    "android": {
      "value": null,
      "comment": "Not explicitly documented"
    },
    "embedded": {
      "value": false,
      "source": ["https://docs.rs/pickledb"],
      "comment": "Requires std"
    },
    "use-cases": {
      "value": ["config-storage", "cli-tool"],
      "source": ["https://github.com/seladb/pickledb-rs"],
      "comment": "Best for simple config storage and small applications"
    },
    "github-stars": {
      "value": 267,
      "source": ["https://github.com/seladb/pickledb-rs"],
      "comment": "As of December 2025"
    },
    "crates-io-downloads": {
      "value": null,
      "comment": "lib.rs shows ~60k/month"
    },
    "last-release": {
      "value": "2022-04-26",
      "source": ["https://lib.rs/crates/pickledb"],
      "comment": "Version 0.5.1"
    },
    "maintenance-status": {
      "value": ["passively-maintained"],
      "source": ["https://github.com/seladb/pickledb-rs"],
      "comment": "Last release April 2022; considered feature-complete"
    },
    "documentation-quality": {
      "value": 3,
      "source": ["https://docs.rs/pickledb"],
      "comment": "Basic API documentation with examples"
    },
    "bus-factor": {
      "value": ["solo"],
      "source": ["https://github.com/seladb"],
      "comment": "seladb is primary maintainer"
    }
  }
}
