{
  "candidates": [
    {
      "id": "rhai",
      "shownByDefault": true
    },
    {
      "id": "mlua",
      "shownByDefault": true
    },
    {
      "id": "rune",
      "shownByDefault": true
    },
    {
      "id": "boa",
      "shownByDefault": true
    },
    {
      "id": "rquickjs",
      "shownByDefault": true
    },
    {
      "id": "gluon",
      "shownByDefault": true
    },
    {
      "id": "dyon",
      "shownByDefault": true
    },
    {
      "id": "rustpython",
      "shownByDefault": true
    },
    {
      "id": "steel",
      "shownByDefault": true
    },
    {
      "id": "piccolo",
      "shownByDefault": true
    }
  ]
}
